method_detect
