Metadata-Version: 2.1
Name: method-detect
Version: 1.9
Summary: YHMediator assistant tool for detect unimplementable method
Home-page: http://gitlab.yonghui.cn/operation-xm-qdjg/yhgit.git
Download-URL: https://files.pythonhosted.org/packages/08/7d/95aa3aa88c4c195889993de691b7fe816ac8d0767ea22fce56ccd240169a/yhmgit-0.3.tar.gz
Author: yonghuifan21
Author-email: jackfan1@yonghui.com
License: MIT
Keywords: method_detect
Classifier: Development Status :: 3 - Alpha
Classifier: Intended Audience :: Developers
Classifier: Topic :: Software Development :: Build Tools
Classifier: License :: OSI Approved :: MIT License
Classifier: Programming Language :: Python :: 3
Classifier: Programming Language :: Python :: 3.4
Classifier: Programming Language :: Python :: 3.5
Classifier: Programming Language :: Python :: 3.6
Requires-Python: >=3.7
Requires-Dist: requests
